c2y/__init__.py
c2y/__main__.py
c2y/utils.py
c2y-0.1.5.dist-info/LICENSE
c2y-0.1.5.dist-info/METADATA
c2y-0.1.5.dist-info/WHEEL
c2y-0.1.5.dist-info/entry_points.txt
c2y-0.1.5.dist-info/RECORD
